ODFex/ODFex.py
ODFex/__init__.py
ODFex/crystal.py
ODFex/default.cif
ODFex/misc.py
ODFex/palettes.py
ODFex/run_ODFex.py
ODFex/spherePlotWindow.py
ODFex/text_editor.py
ODFex/textureSample.py
ODFex/icons/ODFex_logo.ico
ODFex/icons/ODFex_logo.png
ODFex-0.0.2.dist-info/LICENSE
ODFex-0.0.2.dist-info/METADATA
ODFex-0.0.2.dist-info/WHEEL
ODFex-0.0.2.dist-info/entry_points.txt
ODFex-0.0.2.dist-info/top_level.txt
ODFex-0.0.2.dist-info/RECORD
