Metadata-Version: 2.1
Name: ODFex
Version: 0.0.2
Summary: A simple visualization tool intended to help interpret or predict the azimuthal variation in X-ray powder diffraction data
Author-email: Frederik H Gjørup <fgjorup@chem.au.dk>
Project-URL: Homepage, https://github.com/fgjorup/ODFex
Classifier: Programming Language :: Python :: 3
Classifier: License :: OSI Approved :: GNU General Public License (GPL)
Classifier: Operating System :: OS Independent
Classifier: Development Status :: 5 - Production/Stable
Classifier: Intended Audience :: Science/Research
Classifier: Topic :: Education
Classifier: Topic :: Scientific/Engineering
Requires-Python: >=3.9
License-File: LICENSE
Requires-Dist: numpy >=1.24
Requires-Dist: pyqtgraph >=0.13
Requires-Dist: Dans-Diffraction >=2.2.3
Requires-Dist: PyQt6 >=6.7
Requires-Dist: PyOpenGL >=3.1.6
